README.md
setup.py
model_center/__init__.py
model_center/arguments.py
model_center.egg-info/PKG-INFO
model_center.egg-info/SOURCES.txt
model_center.egg-info/dependency_links.txt
model_center.egg-info/requires.txt
model_center.egg-info/top_level.txt
model_center/dataset/__init__.py
model_center/dataset/distributed_dataset.py
model_center/dataset/distributed_indexed.py
model_center/dataset/distributed_loader.py
model_center/dataset/indexed.py
model_center/dataset/utils.py
model_center/dataset/bertdataset/__init__.py
model_center/dataset/bertdataset/superglue.py
model_center/dataset/cpm1/__init__.py
model_center/dataset/cpm1/cpm1_dataset.py
model_center/dataset/cpm1dataset/__init__.py
model_center/dataset/cpm1dataset/down_data.py
model_center/dataset/cpm2/__init__.py
model_center/dataset/cpm2/dataset.py
model_center/dataset/cpm2dataset/__init__.py
model_center/dataset/cpm2dataset/down_data.py
model_center/dataset/gpt2dataset/__init__.py
model_center/dataset/gpt2dataset/superglue.py
model_center/dataset/llamadataset/__init__.py
model_center/dataset/llamadataset/superglue.py
model_center/dataset/t5dataset/__init__.py
model_center/dataset/t5dataset/superglue.py
model_center/generation/__init__.py
model_center/generation/generation_utils.py
model_center/generation/llama.py
model_center/layer/__init__.py
model_center/layer/attention.py
model_center/layer/blocks.py
model_center/layer/conv.py
model_center/layer/embedding.py
model_center/layer/feedforward.py
model_center/layer/layernorm.py
model_center/layer/linear.py
model_center/layer/position_embedding.py
model_center/layer/transformer.py
model_center/model/__init__.py
model_center/model/basemodel.py
model_center/model/bert.py
model_center/model/cpm1.py
model_center/model/cpm2.py
model_center/model/cpm3.py
model_center/model/glm.py
model_center/model/gpt2.py
model_center/model/gptj.py
model_center/model/llama.py
model_center/model/longformer.py
model_center/model/opt.py
model_center/model/roberta.py
model_center/model/t5.py
model_center/model/vit.py
model_center/model/config/__init__.py
model_center/model/config/bert_config.py
model_center/model/config/config.py
