Metadata-Version: 1.0
Name: model-center
Version: 1.0.2
Summary: example codes for big models using bmtrain
Home-page: https://github.com/OpenBMB/ModelCenter
Author: Weilin Zhao
Author-email: acha131441373@gmail.com
License: Apache 2.0
Keywords: CPM,cuda,AI,model,transformer
Platform: UNKNOWN
